plugin_pb_python-0.0.11-py3.11-nspkg.pth
cloudquery/plugin_v3/__init__.py
cloudquery/plugin_v3/plugin_pb2.py
cloudquery/plugin_v3/plugin_pb2.pyi
cloudquery/plugin_v3/plugin_pb2_grpc.py
plugin_pb_python-0.0.11.dist-info/LICENSE
plugin_pb_python-0.0.11.dist-info/METADATA
plugin_pb_python-0.0.11.dist-info/WHEEL
plugin_pb_python-0.0.11.dist-info/namespace_packages.txt
plugin_pb_python-0.0.11.dist-info/top_level.txt
plugin_pb_python-0.0.11.dist-info/RECORD
