Metadata-Version: 2.1
Name: plugin-pb-python
Version: 0.0.11
Summary: CloudQuery Plugin client and server library
Home-page: https://github.com/cloudquery/plugin-pb-python
Author: CloudQuery LTD
Author-email: pypi-packages@cloudquery.io
License: MPL-2.0
Platform: Posix; MacOS X; Windows
Classifier: Intended Audience :: Developers
Classifier: License :: OSI Approved :: Apache Software License
Classifier: Programming Language :: Python
Classifier: Programming Language :: Python :: 3
Classifier: Programming Language :: Python :: 3.7
Classifier: Programming Language :: Python :: 3.8
Classifier: Programming Language :: Python :: 3.9
Classifier: Programming Language :: Python :: 3.10
Classifier: Programming Language :: Python :: 3.11
Classifier: Operating System :: OS Independent
Classifier: Topic :: Internet
Requires-Python: >=3.7
License-File: LICENSE
Requires-Dist: grpcio (>=1.56.0)
Requires-Dist: grpcio-tools (>=1.56.0)
Requires-Dist: protobuf (>=4.23.4)
